JavabeginnerstutorialZhongwenXilieJiaochengChuyi/README.md
JavabeginnerstutorialZhongwenXilieJiaochengChuyi/__init__.py
JavabeginnerstutorialZhongwenXilieJiaochengChuyi/__main__.py
JavabeginnerstutorialZhongwenXilieJiaochengChuyi/file.epub
JavabeginnerstutorialZhongwenXilieJiaochengChuyi/index.html
JavabeginnerstutorialZhongwenXilieJiaochengChuyi/css/__init__.py
JavabeginnerstutorialZhongwenXilieJiaochengChuyi/css/annotations.css
JavabeginnerstutorialZhongwenXilieJiaochengChuyi/css/main.css
JavabeginnerstutorialZhongwenXilieJiaochengChuyi/css/normalize.css
JavabeginnerstutorialZhongwenXilieJiaochengChuyi/css/popup.css
JavabeginnerstutorialZhongwenXilieJiaochengChuyi/font/__init__.py
JavabeginnerstutorialZhongwenXilieJiaochengChuyi/font/fontello.eot
JavabeginnerstutorialZhongwenXilieJiaochengChuyi/font/fontello.svg
JavabeginnerstutorialZhongwenXilieJiaochengChuyi/font/fontello.ttf
JavabeginnerstutorialZhongwenXilieJiaochengChuyi/font/fontello.woff
JavabeginnerstutorialZhongwenXilieJiaochengChuyi/img/__init__.py
JavabeginnerstutorialZhongwenXilieJiaochengChuyi/img/annotator-glyph-sprite.png
JavabeginnerstutorialZhongwenXilieJiaochengChuyi/img/annotator-icon-sprite.png
JavabeginnerstutorialZhongwenXilieJiaochengChuyi/img/apple-touch-icon.png
JavabeginnerstutorialZhongwenXilieJiaochengChuyi/img/cancelfullscreen.png
JavabeginnerstutorialZhongwenXilieJiaochengChuyi/img/close.png
JavabeginnerstutorialZhongwenXilieJiaochengChuyi/img/fullscreen.png
JavabeginnerstutorialZhongwenXilieJiaochengChuyi/img/loader.gif
JavabeginnerstutorialZhongwenXilieJiaochengChuyi/img/menu-icon.png
JavabeginnerstutorialZhongwenXilieJiaochengChuyi/img/save.png
JavabeginnerstutorialZhongwenXilieJiaochengChuyi/img/saved.png
JavabeginnerstutorialZhongwenXilieJiaochengChuyi/img/settings-s.png
JavabeginnerstutorialZhongwenXilieJiaochengChuyi/img/settings.png
JavabeginnerstutorialZhongwenXilieJiaochengChuyi/img/star.png
JavabeginnerstutorialZhongwenXilieJiaochengChuyi/js/__init__.py
javabeginnerstutorial_zhongwen_xilie_jiaocheng_chuyi-2024.3.5.0.dist-info/METADATA
javabeginnerstutorial_zhongwen_xilie_jiaocheng_chuyi-2024.3.5.0.dist-info/WHEEL
javabeginnerstutorial_zhongwen_xilie_jiaocheng_chuyi-2024.3.5.0.dist-info/entry_points.txt
javabeginnerstutorial_zhongwen_xilie_jiaocheng_chuyi-2024.3.5.0.dist-info/top_level.txt
javabeginnerstutorial_zhongwen_xilie_jiaocheng_chuyi-2024.3.5.0.dist-info/RECORD
